.travis.yml
AUTHORS
ChangeLog
LICENSE
README.md
requirements.txt
setup.cfg
setup.py
test-requirements.txt
tox.ini
qg/__init__.py
qg.core.egg-info/PKG-INFO
qg.core.egg-info/SOURCES.txt
qg.core.egg-info/dependency_links.txt
qg.core.egg-info/not-zip-safe
qg.core.egg-info/pbr.json
qg.core.egg-info/requires.txt
qg.core.egg-info/top_level.txt
qg/core/__init__.py
qg/core/exception.py
qg/core/gettextutils.py
qg/core/importutils.py
qg/core/jsonutils.py
qg/core/local.py
qg/core/log.py
qg/core/observer.py
qg/core/singleton.py
qg/core/timeutils.py
qg/core/app/__init__.py
qg/core/app/application.py
qg/core/app/exts/__init__.py
qg/core/app/exts/log.py
tests/__init__.py
tests/locale/zh_CN/LC_MESSAGES/testing.po
tests/unit/__init__.py
tests/unit/test_exception.py
tests/unit/test_ext_log.py
tests/unit/test_gettextutils.py
tests/unit/test_singleton.py
tests/unit/app/__init__.py
tests/unit/app/test_application.py
tests/unit/app/test_extension.py